boosint/__init__.py
boosint/blackbird.py
boosint/boosint.py
boosint/GitRecon/__init__.py
boosint/GitRecon/github_recon.py
boosint/GitRecon/gitrecon.py
boosint/GitRecon/modules/__init__.py
boosint/GitRecon/modules/github_recon.py
boosint/GitRecon/modules/gitlab_recon.py
boosint/modules/__init__.py
boosint/modules/get_info.py
boosint/modules/github.py
boosint/modules/github_recon.py
boosint/modules/gravatar.py
boosint/modules/phone_search.py
boosint/modules/pinterest.py
boosint/modules/reddit.py
boosint/modules/scratch.py
boosint/modules/thatsthem.py
boosint/modules/tiktok.py
boosint/modules/twitter.py
boosint-0.0.3.dist-info/METADATA
boosint-0.0.3.dist-info/WHEEL
boosint-0.0.3.dist-info/top_level.txt
boosint-0.0.3.dist-info/RECORD
