Metadata-Version: 2.1
Name: boosint
Version: 0.0.3
Summary: A powerful username osint tool.
Home-page: UNKNOWN
Author: ProtDos
Author-email: <rootcode@duck.com>
License: UNKNOWN
Keywords: python,osint,detection,information-gathering,maigret,social-media
Platform: UNKNOWN
Classifier: Development Status :: 1 - Planning
Classifier: Intended Audience :: Developers
Classifier: Programming Language :: Python :: 3
Classifier: Operating System :: Unix
Classifier: Operating System :: MacOS :: MacOS X
Classifier: Operating System :: Microsoft :: Windows
Requires-Dist: maigret
Requires-Dist: requests
Requires-Dist: selenium
Requires-Dist: undetected-chromedriver
Requires-Dist: scrape-search-engine
